aws_session_manager/__init__.py
aws_session_manager/__main__.py
aws_session_manager/curses_fix.py
aws_session_manager/session_manager.py
aws_session_manager-1.2.1.dist-info/LICENSE
aws_session_manager-1.2.1.dist-info/METADATA
aws_session_manager-1.2.1.dist-info/WHEEL
aws_session_manager-1.2.1.dist-info/top_level.txt
aws_session_manager-1.2.1.dist-info/RECORD
