Metadata-Version: 2.2
Name: aws_session_manager
Version: 1.2.1
Summary: A command line UI to manage AWS Session Manager sessions
Author-email: Hélio Santos <heliosantos99@gmail.com>
Classifier: Programming Language :: Python :: 3.9
Classifier: Programming Language :: Python :: 3.10
Classifier: Programming Language :: Python :: 3.11
Classifier: Programming Language :: Python :: 3.12
Classifier: Programming Language :: Python :: 3.13
Classifier: License :: OSI Approved :: MIT License
Classifier: Operating System :: OS Independent
Requires-Python: >=3.9
License-File: LICENSE
Requires-Dist: PyYAML
Requires-Dist: curses; platform_system == "Linux"
Requires-Dist: curses; platform_system == "Darwin"
Requires-Dist: windows-curses; platform_system == "Windows"
